esneft_tools/__init__.py
esneft_tools/download.py
esneft_tools/process.py
esneft_tools/synthetic.py
esneft_tools/utils.py
esneft_tools/visualise.py
esneft_tools-0.1.4.dist-info/LICENSE
esneft_tools-0.1.4.dist-info/METADATA
esneft_tools-0.1.4.dist-info/WHEEL
esneft_tools-0.1.4.dist-info/top_level.txt
esneft_tools-0.1.4.dist-info/RECORD
