Metadata-Version: 2.1
Name: esneft-tools
Version: 0.1.4
Summary: Utilities to analyse population and deprivation data.
Author: Stephen Richer
Author-email: stephen.richer@nhs.net
License: MIT License
Project-URL: repository, https://github.com/nhsx/p24-pvt-diabetes-inequal
Keywords: esneft_tools
Classifier: Natural Language :: English
Classifier: Intended Audience :: Science/Research
Classifier: Intended Audience :: Healthcare Industry
Classifier: Development Status :: 1 - Planning
Classifier: License :: OSI Approved :: MIT License
Classifier: Programming Language :: Python :: 3
Classifier: Programming Language :: Python :: 3.7
Classifier: Programming Language :: Python :: 3.8
Classifier: Programming Language :: Python :: 3.9
Classifier: Programming Language :: Python :: 3.10
Classifier: Programming Language :: Python :: 3.11
Requires-Python: >=3.7
License-File: LICENSE
Requires-Dist: numpy
Requires-Dist: pyyaml
Requires-Dist: plotly
Requires-Dist: pandas
Requires-Dist: pyarrow
Requires-Dist: seaborn
Requires-Dist: kaleido
Requires-Dist: openpyxl
Requires-Dist: matplotlib
Provides-Extra: geo
Requires-Dist: geopandas ; extra == 'geo'
Requires-Dist: fiona ; extra == 'geo'
Requires-Dist: pyproj ; extra == 'geo'
Requires-Dist: networkx ; extra == 'geo'
